---
title: java基础中
date: 2022-07-09 15:35:05
permalink: /pages/83cf38/
categories:
  - 八股文
  - Java
  - 基础
tags:
  - 
---

# 关于java中一些基础面试题(中)

## 面向对象

### 面向对象的三大特征

#### 封装
::: tip 封装
封装是面向对象编程的核心思想，将对象的属性和行为封装隐藏起来。而这些封装起来的属性和行为通常对外隐藏细节，只允许外部使用公开的数据，避免外部操作导致内部数据改变，来保证类内部数据和结果的完整性，提高程序的可维护性。
~~~java
public class Student {
    private int id;
    private String name;

    
    public int getId() {
        return id;
    }

    
    public void setId(int id) {
        this.id = id;
    }

    
    public String getName() {
        return name;
    }

    //设置name的方法
    public void setName(String name) {
        this.name = name;
    }
}
~~~
封装其实字面意思也就是很好理解，但是理解是一回事而在程序中更为复杂的使用对于0基础的小伙伴还是蒙蒙的。给小伙伴举个简单的例子:
就拿我们的手机来说，你看不到里面的各种零件各种芯片，你也不知道他们怎么实现的。但是呢通过你点击屏幕会呈现给你相应的展示和结果。
这个例子不是很恰当，但是要表达的意思就是那个意思。希望对小伙伴有个好的理解。
:::

#### 继承
::: tip 继承
不同的对象，对于各自属性有一定的相同点。你比如说 奥迪汽车，大众汽车，领克汽车。那他们都有汽车的特性(发动机，轮子，方向盘等等)
但是每个品牌的汽车可能还会有他们自己独有的特性，那比如一辆汽车有全景天窗，一辆却没有。而**继承**呢就是可以将一个已存在的类作为基础
而新类可以去继承这个已存在的，从而获取一些新的数据及功能。**但不能选择性地继承父类。通过使用继承，可以快速地创建新的类，可以提高代码的重用，程序的可维护性，节省大量创建新类的时间 ，提高我们的开发效率。**
::: tip 注意
1. 子类拥有父类对象所有的属性和方法（包括私有属性和私有方法），但是父类中的私有属性和方法子类是无法访问，只是拥有。
2. 子类可以拥有自己属性和方法，即子类可以对父类进行扩展。
3. 子类可以用自己的方式实现父类的方法。（以后介绍）。
:::
#### 多态
::: tip 多态
多态多态意思不就是多种状态嘛，在完善一下就是**一个对象/类有多种不同的实现，多种形式来展现。

::: tip 特点
1. 对象类型和引用类型之间具有继承（类）/实现（接口）的关系；
2. 引用类型变量发出的方法调用的到底是哪个类中的方法，必须在程序运行期间才能确定；
3. 多态不能调用“只在子类存在但在父类不存在”的方法；
4. 如果子类重写了父类的方法，真正执行的是子类覆盖的方法，如果子类没有覆盖父类的方法，执行的是父类的方法。
:::

::: tip 优点
1. 消除类型之间的耦合关系
2. 可替换性
3. 灵活性
4. 简化性
:::

:::

### 接口和抽象类有什么共同点和区别?

#### 不同点

1. 定义接口关键字是: **interface**,而定义抽象类关键字是: **abstract**
2. 接口里面只能做方法声明，而抽象类里面可以做方法声明还可以做方法体实现
3. 接口中的成员变量只能是 public static final 类型的，不能被修改且必须有初始值，而抽象类的成员变量默认 default，可在子类中被重新定义，也可被重新赋值。
4. 一个类只能继承一个类，但是可以实现多个接口。

#### 共同点
1. 都不能被实例化。
2. 都可以包含抽象方法。
3. 都可以有默认实现的方法（Java 8 可以用 default 关键在接口中定义默认方法）。

### 浅拷贝和深拷贝有什么不同？
::: tip 总结
* **浅拷贝:** 被复制对象的所有值属性都含有与原来对象的相同，而所有的对象引用属性仍然指向原来的对象。
可能有点绕那简单来说，A对象被拷贝得到新对象B。对于B对象来说里面的属性都和A一样。同时在使用B对象时修改里面属性的值不会影响原有对象A
::: tip 注意:
当A对象中存在引用类型的属性，浅拷贝会直接复制内部对象的引用地址，也就是说拷贝对象和原对象共用同一个内部对象(**这种情况修改了属性的值的话会影响原有对象里面的值**)。
:::

* **深拷贝:** 深拷贝会完全复制整个对象，包括这个对象所包含的内部对象。

1. 浅拷贝例子:
~~~java
public class Student implements Cloneable {
    private String name;
    private Integer age;
    private Teacher teacher;

    @Override
    public Object clone(){
        Student stu = null;
        try {
            
            stu = (Student) super.clone();
        } catch (CloneNotSupportedException e) {
            e.printStackTrace();
        }
        return stu;
    }
}

++++++++++++++++++++++++++++++++++++++++++++++++++++++++++++++++
        Student student=new Student();
        student.setAge(15);
        student.setName("王不正");

        Teacher teacher=new Teacher();
        teacher.setSex("男");
        teacher.setTeacherName("爱学习的王不正");

        student.setTeacher(teacher);


        /**
         * 第一: 由此结果看出： 都指向相同的对象，这叫做: 引用拷贝
         */
        Student student1=student;
        System.out.println("student==student1: "+(student==student1));
        System.out.println(student);
        System.out.println(student1);


        /**
         * 第二:
         */
        Student student2=(Student) student.clone();
        System.out.println("克隆后的结果:============================================");
        System.out.println(student2.getAge());
        System.out.println(student2.getName());
        System.out.println(student2.getTeacher().getSex());
        System.out.println(student2.getTeacher().getTeacherName());

        //此时修改:student中的值
        student.setName("自闭王不正");

        System.out.println("修改student值后的结果:============================================");
        System.out.println(student2.getAge());
        System.out.println("student2中的name值:"+student2.getName());
        System.out.println("student1中的name值:"+student.getName());
        System.out.println(student2.getTeacher().getSex());
        System.out.println(student2.getTeacher().getTeacherName());

        //此时修改: student中引用对象teacher的值
        teacher.setTeacherName("学习很厉害的王不正");

        System.out.println("修改studenet中引用对象teacher值后的结果:============================================");
        System.out.println(student2.getAge());
        System.out.println(student2.getName());
        System.out.println(student2.getTeacher().getSex());
        System.out.println("student2中的name值:"+student2.getTeacher().getTeacherName());
        System.out.println("student1中的name值:"+student.getTeacher().getTeacherName());
~~~
1.1 运行结果
~~~java
student==student1: true
com.javaleran.java克隆Clone.test.浅克隆.pojo.Student@8efb846
com.javaleran.java克隆Clone.test.浅克隆.pojo.Student@8efb846
克隆后的结果:============================================
15
王不正
男
爱学习的王不正
修改student值后的结果:============================================
15
student2中的name值:王不正
student1中的name值:自闭王不正
男
爱学习的王不正
修改studenet中引用对象teacher值后的结果:============================================
15
王不正
男
student2中的name值:学习很厉害的王不正
student1中的name值:学习很厉害的王不正
~~~
:::

2. 深拷贝例子: 

~~~java
public class Student implements Cloneable {
    private String name;
    private Integer age;
    private Teacher teacher;

    @Override
    public Object clone(){
        Student stu = null;
        try {
            stu = (Student) super.clone();
            //深克隆
            stu.setTeacher((Teacher) stu.getTeacher().clone());
        } catch (CloneNotSupportedException e) {
            e.printStackTrace();
        }
        return stu;
    }

//老师类
public class Teacher implements Cloneable{

    private String teacherName;
    private String sex;
    @Override
    public Object clone(){
        Teacher stu = null;
        try {
            //浅克隆
            stu = (Teacher) super.clone();
        } catch (CloneNotSupportedException e) {
            e.printStackTrace();
        }
        return stu;
    }

++++++++++++++++++++++++++++++++++++++++++++++++++++++++++++++++
        Student student=new Student();
        student.setAge(15);
        student.setName("王不正");

        Teacher teacher=new Teacher();
        teacher.setSex("男");
        teacher.setTeacherName("爱学习的王不正");

        student.setTeacher(teacher);


        /**
         * 第一: 由此结果看出： 都指向相同的对象，这叫做: 引用拷贝
         */
        Student student1=student;
        System.out.println("student==student1: "+(student==student1));
        System.out.println(student);
        System.out.println(student1);


        /**
         * 第二:
         */
        Student student2=(Student) student.clone();
        System.out.println("克隆后的结果:============================================");
        System.out.println(student2.getAge());
        System.out.println(student2.getName());
        System.out.println(student2.getTeacher().getSex());
        System.out.println(student2.getTeacher().getTeacherName());

        //此时修改:student中的值
        student.setName("自闭王不正");

        System.out.println("修改student值后的结果:============================================");
        System.out.println(student2.getAge());
        System.out.println("student2中的name值:"+student2.getName());
        System.out.println("student1中的name值:"+student.getName());
        System.out.println(student2.getTeacher().getSex());
        System.out.println(student2.getTeacher().getTeacherName());

        //此时修改: student中引用对象teacher的值
        teacher.setTeacherName("学习很厉害的王不正");

        System.out.println("修改studenet中引用对象teacher值后的结果:============================================");
        System.out.println(student2.getAge());
        System.out.println(student2.getName());
        System.out.println(student2.getTeacher().getSex());
        System.out.println("student2中的name值:"+student2.getTeacher().getTeacherName());
        System.out.println("student1中的name值:"+student.getTeacher().getTeacherName());
~~~
2.2 运行结果
~~~java
克隆后的结果:============================================
15
王不正
男
爱学习的王不正
修改student值后的结果:============================================
15
student2中的name值:王不正
student1中的name值:自闭王不正
男
爱学习的王不正
修改studenet中引用对象teacher值后的结果:============================================
15
王不正
男
student2中的name值:爱学习的王不正
student1中的name值:学习很厉害的王不正
~~~

## ==与equals()的区别

1. **==** 对于基本类型和引用类型的作用效果是不同的：
* 对于基本数据类型来说，== 比较的是值。
* 对于引用数据类型来说，== 比较的是对象的内存地址。

2. **equals()** 属于Object类的方法，如果我们没有重写过equals方法，那么它就是 ==，但是字符串里面的equals被重写过了，比较的是值

3. 代码一:
~~~java
        String s="ab";
        String s1="ab";
        String s2=new String("az");
        String s3=new String("az");
        String s4="hello";
        String s5="he"+"llo";
        
        System.out.println(s == s1); //true 
        System.out.println(s.equals(s1));//true

        System.out.println(s2 == s3);//false （==：如果是new出来的对象，比较的时候永远是false）
        System.out.println(s2.equals(s3)); //true

        System.out.println(s4 == s5);//true
        System.out.println(s4.equals(s5));//true
~~~

## String、StringBuffer、StringBuilder 的区别？
1. 可变性
* String 是不可变的。因为被final修饰

* StringBuilder 与 StringBuffer 都继承自 AbstractStringBuilder 类，在 AbstractStringBuilder 中也是使用字符数组保存字符串，不过没有使用 final 和 private 关键字修饰，最关键的是这个 AbstractStringBuilder 类还提供了很多修改字符串的方法比如 append 方法。

2. 线程安全性
* String 中的对象是不可变的，也就可以理解为常量，线程安全。AbstractStringBuilder 是 StringBuilder 与 StringBuffer 的公共父类，定义了一些字符串的基本操作，如 expandCapacity、append、insert、indexOf 等公共方法。StringBuffer 对方法加了同步锁或者对调用的方法加了同步锁，所以是线程安全的。StringBuilder 并没有对方法进行加同步锁，所以是非线程安全的。


## String "+" 的操作原理?
1. 代码一:
~~~java
        String str1 = "he";
        String str2 = "llo";
        String str3 = "world";
        String str4 = str1 + str2 + str3;
~~~
编译过后:
~~~java
public static void main(java.lang.String[]);
    Code:
       0: ldc           #2                  // String he
       2: astore_1
       3: ldc           #3                  // String llo
       5: astore_2
       6: ldc           #4                  // String world
       8: astore_3
       9: new           #5                  // class java/lang/StringBuilder
      12: dup
      13: invokespecial #6                  // Method java/lang/StringBuilder."<init>":()V
      16: aload_1
      17: invokevirtual #7                  // Method java/lang/StringBuilder.append:(Ljava/lang/String;)Ljava/lang/StringBuilder;
      20: aload_2
      21: invokevirtual #7                  // Method java/lang/StringBuilder.append:(Ljava/lang/String;)Ljava/lang/StringBuilder;
      24: aload_3
      25: invokevirtual #7                  // Method java/lang/StringBuilder.append:(Ljava/lang/String;)Ljava/lang/StringBuilder;
      28: invokevirtual #8                  // Method java/lang/StringBuilder.toString:()Ljava/lang/String;
      31: astore        4
      33: return
~~~
::: tip 代码一总结
编译过后可以看到，内部是通过StringBuilder的append方法进行拼接。然后通过toString()方法得到String对象。
但是有一个问题，上述代码中我们只是单纯的一个String对象。那假如一段代码循环中写了String +的操作。那可想而知性能
是大大的拉跨，因为你循环一次就要创建一个StringBuilder。所以不如直接在循环外使用StringBuilder。
:::

## String 为什么不可变?
::: tip 总结
1. 保存字符串的数组被 final 修饰且为私有的，并且String 类没有提供/暴露修改这个字符串的方法。
2. String 类被 final 修饰导致其不能被继承，进而避免了子类破坏 String 不可变。
:::

## 参考
<a href="https://snailclimb.gitee.io/javaguide/#/docs/java/basis/java-basic-questions-01?id=%e5%9f%ba%e7%a1%80%e6%a6%82%e5%bf%b5%e4%b8%8e%e5%b8%b8%e8%af%86">https://snailclimb.gitee.io/javaguide/#/docs/java/basis/java-basic-questions-01?id=%e5%9f%ba%e7%a1%80%e6%a6%82%e5%bf%b5%e4%b8%8e%e5%b8%b8%e8%af%86</a>
<a href="https://juejin.cn/post/6909066772721172488#heading-3">https://juejin.cn/post/6909066772721172488#heading-3</a>